cli.py
dynamo_json.py
dynamo_json-1.2.0.dist-info/LICENSE
dynamo_json-1.2.0.dist-info/METADATA
dynamo_json-1.2.0.dist-info/WHEEL
dynamo_json-1.2.0.dist-info/entry_points.txt
dynamo_json-1.2.0.dist-info/top_level.txt
dynamo_json-1.2.0.dist-info/RECORD
