Metadata-Version: 2.1
Name: dynamo-json
Version: 1.2.0
Summary: Swap between DynamoDB JSON and normal JSON
Home-page: https://github.com/adilosa/dynamo-json
Author: adilosa
License: UNKNOWN
Project-URL: Bug Reports, https://github.com/adilosa/dynamo-json/issues
Project-URL: Say Thanks!, http://saythanks.io/to/adilosa
Project-URL: Source, https://github.com/adilosa/dynamo-json/
Keywords: dynamo json dynamodb
Platform: UNKNOWN
Classifier: Development Status :: 3 - Alpha
Classifier: Intended Audience :: Developers
Classifier: Topic :: Software Development :: Libraries :: Python Modules
Classifier: License :: OSI Approved :: MIT License
Classifier: Programming Language :: Python :: 3
Classifier: Programming Language :: Python :: 3.4
Classifier: Programming Language :: Python :: 3.5
Classifier: Programming Language :: Python :: 3.6
Classifier: Programming Language :: Python :: 3.7
Classifier: Programming Language :: Python :: 3.8
